py_candlestick/__init__.py
py_candlestick/candle.py
py_candlestick/chart.py
py_candlestick/defaults.py
py_candlestick/extensions.py
py_candlestick/indicator_calculators.py
py_candlestick/series.py
py_candlestick/symbol.py
py_candlestick/time_frame.py
py_candlestick-0.1.1.dist-info/licenses/LICENSE
tests/__init__.py
tests/candle_tests.py
tests/chart_tests.py
tests/fixtures.py
py_candlestick-0.1.1.dist-info/METADATA
py_candlestick-0.1.1.dist-info/WHEEL
py_candlestick-0.1.1.dist-info/top_level.txt
py_candlestick-0.1.1.dist-info/RECORD
