Metadata-Version: 2.4
Name: py_candlestick
Version: 0.1.1
Summary: A pythonic package for working with market data
Home-page: https://github.com/s0hei1/py_candlestick
Author: Soheil Hesari Khosroshahi
Author-email: Soheil Hesari Khosroshahi <khosroshahisoheil@gmail.com>
License:                                  Apache License
Project-URL: Homepage, https://github.com/s0hei1/py_candlestick
Requires-Python: >=3.7
License-File: LICENSE
Requires-Dist: MetaTrader5
Requires-Dist: pandas>=2.0
Requires-Dist: numpy>=1.24
Requires-Dist: more-itertools>=10.0
Dynamic: license-file
